yomemoai_mcp/__init__.py
yomemoai_mcp/client.py
yomemoai_mcp/py.typed
yomemoai_mcp/server.py
yomemoai_mcp-0.1.3.dist-info/METADATA
yomemoai_mcp-0.1.3.dist-info/WHEEL
yomemoai_mcp-0.1.3.dist-info/entry_points.txt
yomemoai_mcp-0.1.3.dist-info/licenses/LICENSE
yomemoai_mcp-0.1.3.dist-info/RECORD
