Metadata-Version: 2.4
Name: yomemoai-mcp
Version: 0.1.3
Summary: Model Context Protocol (MCP) server for YoMemoAI - enables AI assistants to save and retrieve encrypted memories
Project-URL: Homepage, https://github.com/yomemoai/python-yomemo-mcp
Project-URL: Documentation, https://github.com/yomemoai/python-yomemo-mcp#readme
Project-URL: Repository, https://github.com/yomemoai/python-yomemo-mcp
Project-URL: Issues, https://github.com/yomemoai/python-yomemo-mcp/issues
Author-email: xxlv <lvxiang119@gmail.com>
License: MIT
License-File: LICENSE
Keywords: ai,claude,cursor,mcp,mcp-server,memory,yomemoai
Classifier: Development Status :: 4 - Beta
Classifier: Intended Audience :: Developers
Classifier: License :: OSI Approved :: MIT License
Classifier: Programming Language :: Python :: 3
Classifier: Programming Language :: Python :: 3.12
Classifier: Topic :: Scientific/Engineering :: Artificial Intelligence
Classifier: Topic :: Software Development :: Libraries :: Python Modules
Requires-Python: >=3.12
Requires-Dist: cryptography>=46.0.3
Requires-Dist: fastmcp>=0.1.0
Requires-Dist: mcp>=1.25.0
Requires-Dist: python-dotenv>=1.2.1
Requires-Dist: requests>=2.32.5
